{
  "project_info": {
    "project_number": "328512445103",
    "firebase_url": "https://poupe-pila.firebaseio.com",
    "project_id": "poupe-pila",
    "storage_bucket": "poupe-pila.appspot.com"
  },
  "client": [
    {
      "client_info": {
        "mobilesdk_app_id": "1:328512445103:android:6edddd7e44415ec0dc525a",
        "android_client_info": {
          "package_name": "com.poupepilla.poupe_pila"
        }
      },
      "oauth_client": [
        {
          "client_id": "328512445103-s7djb3eb2iob9tab16kuvhm11t6qjijr.apps.googleusercontent.com",
          "client_type": 3
        }
      ],
      "api_key": [
        {
          "current_key": "AIzaSyAXu2WEdo5j0tR7WILf6fvg7_3H3lxlTOs"
        }
      ],
      "services": {
        "appinvite_service": {
          "other_platform_oauth_client": [
            {
              "client_id": "328512445103-s7djb3eb2iob9tab16kuvhm11t6qjijr.apps.googleusercontent.com",
              "client_type": 3
            }
          ]
        }
      }
    }
  ],
  "configuration_version": "1"
}